{
    "6589e42f1261c": {
        "username": "admin",
        "email": "admin@gmail.com",
        "password": "$2y$10$ydgojm9BkIwQIoKyD932DeZIY8O8DlLo86pM9hd7055P9QJ\/gTGRy",
        "balance": 0,
        "cards": [
            "6588a37ddc38d",
            "6588a45bf2c68",
            "6588a45bf2c7a",
            "6588a45bf2c7b",
            "6588a45bf2c7c",
            "65b96bc7d8cae"
        ],
        "roles": [
            "admin"
        ],
        "id": "6589e42f1261c"
    },
    "65b96bfeded2b": {
        "username": "mark",
        "email": "mark@gmail.com",
        "password": "$2y$10$PyLoz1foDGEcTdzlChjBuOeDkiXeP\/J\/yjDDDGZcr9vuQKDu7Byia",
        "balance": 312.5,
        "cards": [
            "6588a45bf2c79",
            "6588a45bf2c7d",
            "6588a45bf2c76",
            "6588a335149ac",
            "6588a45bf2c78"
        ],
        "roles": [
            "user"
        ],
        "id": "65b96bfeded2b"
    }
}